patent_client/__init__.py
patent_client/_async/__init__.py
patent_client/_async/epo/__init__.py
patent_client/_async/epo/ops/__init__.py
patent_client/_async/epo/ops/family/__init__.py
patent_client/_async/epo/ops/family/api.py
patent_client/_async/epo/ops/family/api_test.py
patent_client/_async/epo/ops/family/fixtures/family_api_output.json
patent_client/_async/epo/ops/family/fixtures/family_convert.json
patent_client/_async/epo/ops/family/fixtures/family_input.xml
patent_client/_async/epo/ops/family/fixtures/family_model_output.json
patent_client/_async/epo/ops/family/manager.py
patent_client/_async/epo/ops/family/model.py
patent_client/_async/epo/ops/family/model_test.py
patent_client/_async/epo/ops/family/schema.py
patent_client/_async/epo/ops/family/schema_test.py
patent_client/_async/epo/ops/legal/__init__.py
patent_client/_async/epo/ops/legal/api.py
patent_client/_async/epo/ops/legal/api_test.py
patent_client/_async/epo/ops/legal/fixtures/example_1.xml
patent_client/_async/epo/ops/legal/fixtures/example_1_convert.json
patent_client/_async/epo/ops/legal/fixtures/example_2.xml
patent_client/_async/epo/ops/legal/fixtures/example_2_convert.json
patent_client/_async/epo/ops/legal/fixtures/example_3.xml
patent_client/_async/epo/ops/legal/fixtures/example_3_convert.json
patent_client/_async/epo/ops/legal/fixtures/legal_code_descriptions_202417.xlsx
patent_client/_async/epo/ops/legal/manager.py
patent_client/_async/epo/ops/legal/model.py
patent_client/_async/epo/ops/legal/national_codes.py
patent_client/_async/epo/ops/legal/national_codes_test.py
patent_client/_async/epo/ops/legal/schema.py
patent_client/_async/epo/ops/legal/schema_test.py
patent_client/_async/epo/ops/legal/util.py
patent_client/_async/epo/ops/number_service/__init__.py
patent_client/_async/epo/ops/number_service/api.py
patent_client/_async/epo/ops/number_service/api_test.py
patent_client/_async/epo/ops/number_service/errors.py
patent_client/_async/epo/ops/number_service/errors.txt
patent_client-5.0.19.dist-info/AUTHORS.md
patent_client-5.0.19.dist-info/LICENSE
patent_client-5.0.19.dist-info/METADATA
patent_client-5.0.19.dist-info/WHEEL
patent_client-5.0.19.dist-info/RECORD
