Metadata-Version: 2.1
Name: patent_client
Version: 5.0.19
Summary: A set of ORM-style clients for publicly available intellectual property data
Home-page: https://github.com/parkerhancock/patent_client
License: Apache Software License 2.0
Keywords: patent,intellectual property,usitc,epo,ops,trademark,inpadoc,337
Author: Parker Hancock
Author-email: 633163+parkerhancock@users.noreply.github.com
Requires-Python: >=3.9,<3.13
Classifier: Development Status :: 5 - Production/Stable
Classifier: Intended Audience :: End Users/Desktop
Classifier: Intended Audience :: Legal Industry
Classifier: Intended Audience :: Science/Research
Classifier: License :: OSI Approved :: Apache Software License
Classifier: License :: Other/Proprietary License
Classifier: Programming Language :: Python :: 3
Classifier: Programming Language :: Python :: 3.9
Classifier: Programming Language :: Python :: 3.10
Classifier: Programming Language :: Python :: 3.11
Classifier: Programming Language :: Python :: 3.12
Classifier: Topic :: Scientific/Engineering
Requires-Dist: async-property (>=0.2.2,<0.3.0)
Requires-Dist: hishel (>=0.0.26,<0.0.27)
Requires-Dist: httpx[http2] (>=0.27.0,<0.28.0)
Requires-Dist: inflection (>=0.5.1,<0.6.0)
Requires-Dist: lxml (>=5.2.2,<6.0.0)
Requires-Dist: openpyxl (>=3.1.2,<4.0.0)
Requires-Dist: pydantic (>=2.7.1,<3.0.0)
Requires-Dist: pydantic-settings (>=2.2.1,<3.0.0)
Requires-Dist: pypdf (>=4.2.0,<5.0.0)
Requires-Dist: python-dateutil (>=2.9.0.post0,<3.0.0)
Requires-Dist: yankee (>=0.1.46,<0.2.0)
Project-URL: Documentation, https://patent-client.readthedocs.io
Project-URL: Repository, https://github.com/parkerhancock/patent_client
